tkinter_math/__init__.py
tkinter_math/core.py
tkinter_math/data.py
tkinter_math-0.2.4.dist-info/LICENSE
tkinter_math-0.2.4.dist-info/METADATA
tkinter_math-0.2.4.dist-info/WHEEL
tkinter_math-0.2.4.dist-info/top_level.txt
tkinter_math-0.2.4.dist-info/RECORD
