Metadata-Version: 2.1
Name: tkinter-math
Version: 0.2.4
Summary: render math on tkinter canvas
Home-page: https://github.com/K1DV5/tkinter-math
Author: Kidus Adugna
Author-email: kidusadugna@gmail.com
License: MIT license
Keywords: docal,tkinter,math
Platform: UNKNOWN
Classifier: Intended Audience :: Developers
Classifier: License :: OSI Approved :: MIT License
Classifier: Natural Language :: English
Classifier: Programming Language :: Python :: 3
Classifier: Programming Language :: Python :: 3.6
Classifier: Programming Language :: Python :: 3.7
Classifier: Programming Language :: Python :: 3.8
